pypass/__init__.py
pypass/encryption.py
pypass/login.py
pypass/main.py
pypass/ui.py
pypass/vault.py
pypass/icons/eye.png
pypass/icons/eye_gray.png
pypass_secure-0.0.3.dist-info/licenses/LICENSE
pypass_secure-0.0.3.dist-info/METADATA
pypass_secure-0.0.3.dist-info/WHEEL
pypass_secure-0.0.3.dist-info/entry_points.txt
pypass_secure-0.0.3.dist-info/top_level.txt
pypass_secure-0.0.3.dist-info/RECORD
