Metadata-Version: 2.4
Name: pypass-secure
Version: 0.0.3
Summary: Local, offline password manager for Windows with CustomTkinter GUI
Author: rewind
License: MIT License
Project-URL: Homepage, https://github.com/rewindthetime/pypass
Project-URL: Repository, https://github.com/rewindthetime/pypass
Project-URL: Issues, https://github.com/rewindthetime/pypass/issues
Keywords: password,manager,security,encryption,offline,cross-platform
Classifier: Development Status :: 3 - Alpha
Classifier: Intended Audience :: End Users/Desktop
Classifier: License :: OSI Approved :: MIT License
Classifier: Operating System :: Microsoft :: Windows
Classifier: Operating System :: POSIX :: Linux
Classifier: Programming Language :: Python :: 3
Classifier: Programming Language :: Python :: 3.10
Classifier: Programming Language :: Python :: 3.11
Classifier: Programming Language :: Python :: 3.12
Classifier: Topic :: Security :: Cryptography
Classifier: Topic :: Utilities
Requires-Python: >=3.10
License-File: LICENSE
Requires-Dist: cryptography>=41.0.0
Requires-Dist: customtkinter>=5.2.0
Requires-Dist: pillow>=10.0.0
Provides-Extra: dev
Requires-Dist: pyinstaller>=6.0.0; extra == "dev"
Dynamic: license-file
